{
  "lastUpdate": "2021-11-09",
  "history": [
    {
      "statusDate": "2021-10-26",
      "vaccinationRate": 127.42663901036046,
      "vaccinatedPersons": 17442,
      "administeredVaccineDoses": 11015629
    },
    {
      "statusDate": "2021-10-27",
      "vaccinationRate": 127.65508000698233,
      "vaccinatedPersons": 19748,
      "administeredVaccineDoses": 11035377
    },
    {
      "statusDate": "2021-10-28",
      "vaccinationRate": 127.840858941849,
      "vaccinatedPersons": 16060,
      "administeredVaccineDoses": 11051437
    },
    {
      "statusDate": "2021-10-29",
      "vaccinationRate": 128.07421625524034,
      "vaccinatedPersons": 20173,
      "administeredVaccineDoses": 11071610
    },
    {
      "statusDate": "2021-10-30",
      "vaccinationRate": 128.17403483736766,
      "vaccinatedPersons": 8629,
      "administeredVaccineDoses": 11080239
    },
    {
      "statusDate": "2021-10-31",
      "vaccinationRate": 128.1815423422698,
      "vaccinatedPersons": 649,
      "administeredVaccineDoses": 11080888
    },
    {
      "statusDate": "2021-11-01",
      "vaccinationRate": 128.28695974161226,
      "vaccinatedPersons": 9113,
      "administeredVaccineDoses": 11090001
    },
    {
      "statusDate": "2021-11-02",
      "vaccinationRate": 128.4396778921795,
      "vaccinatedPersons": 13202,
      "administeredVaccineDoses": 11103203
    },
    {
      "statusDate": "2021-11-03",
      "vaccinationRate": 128.6134841497369,
      "vaccinatedPersons": 15025,
      "administeredVaccineDoses": 11118228
    },
    {
      "statusDate": "2021-11-04",
      "vaccinationRate": 128.75500466587383,
      "vaccinatedPersons": 12234,
      "administeredVaccineDoses": 11130462
    },
    {
      "statusDate": "2021-11-05",
      "vaccinationRate": 128.94232211869422,
      "vaccinatedPersons": 16193,
      "administeredVaccineDoses": 11146655
    },
    {
      "statusDate": "2021-11-06",
      "vaccinationRate": 129.04261498079222,
      "vaccinatedPersons": 8670,
      "administeredVaccineDoses": 11155325
    },
    {
      "statusDate": "2021-11-07",
      "vaccinationRate": 129.04816752679073,
      "vaccinatedPersons": 480,
      "administeredVaccineDoses": 11155805
    },
    {
      "statusDate": "2021-11-08",
      "vaccinationRate": 129.18198388535473,
      "vaccinatedPersons": 11568,
      "administeredVaccineDoses": 11167373
    },
    {
      "statusDate": "2021-11-09",
      "vaccinationRate": 0,
      "vaccinatedPersons": 0,
      "administeredVaccineDoses": 0
    }
  ]
}